cdk_metaflow/__init__.py
cdk_metaflow/py.typed
cdk_metaflow/_jsii/__init__.py
cdk_metaflow/_jsii/cdk-metaflow@0.0.20.jsii.tgz
cdk_metaflow-0.0.20.dist-info/LICENSE
cdk_metaflow-0.0.20.dist-info/METADATA
cdk_metaflow-0.0.20.dist-info/WHEEL
cdk_metaflow-0.0.20.dist-info/top_level.txt
cdk_metaflow-0.0.20.dist-info/RECORD
