Metadata-Version: 2.1
Name: cdk-metaflow
Version: 0.0.20
Summary: A JSII construct library to build Metaflow infrastructure on AWS using Python, Typescript or Go
Home-page: https://github.com/bcgalvin/metaflow-cdk
Author: bcgalvin<bcgalvin@gmail.com>
License: Apache-2.0
Project-URL: Source, https://github.com/bcgalvin/metaflow-cdk
Platform: UNKNOWN
Classifier: Intended Audience :: Developers
Classifier: Operating System :: OS Independent
Classifier: Programming Language :: JavaScript
Classifier: Programming Language :: Python :: 3 :: Only
Classifier: Programming Language :: Python :: 3.6
Classifier: Programming Language :: Python :: 3.7
Classifier: Programming Language :: Python :: 3.8
Classifier: Programming Language :: Python :: 3.9
Classifier: Typing :: Typed
Classifier: Development Status :: 4 - Beta
Classifier: License :: OSI Approved
Requires-Python: >=3.6
License-File: LICENSE
Requires-Dist: aws-cdk.aws-apigateway (<2.0.0,>=1.126.0)
Requires-Dist: aws-cdk.aws-batch (<2.0.0,>=1.126.0)
Requires-Dist: aws-cdk.aws-cloudwatch (<2.0.0,>=1.126.0)
Requires-Dist: aws-cdk.aws-dynamodb (<2.0.0,>=1.126.0)
Requires-Dist: aws-cdk.aws-ec2 (<2.0.0,>=1.126.0)
Requires-Dist: aws-cdk.aws-ecs (<2.0.0,>=1.126.0)
Requires-Dist: aws-cdk.aws-elasticloadbalancingv2 (<2.0.0,>=1.126.0)
Requires-Dist: aws-cdk.aws-events (<2.0.0,>=1.126.0)
Requires-Dist: aws-cdk.aws-iam (<2.0.0,>=1.126.0)
Requires-Dist: aws-cdk.aws-lambda (<2.0.0,>=1.126.0)
Requires-Dist: aws-cdk.aws-logs (<2.0.0,>=1.126.0)
Requires-Dist: aws-cdk.aws-rds (<2.0.0,>=1.126.0)
Requires-Dist: aws-cdk.aws-s3 (<2.0.0,>=1.126.0)
Requires-Dist: aws-cdk.aws-secretsmanager (<2.0.0,>=1.126.0)
Requires-Dist: aws-cdk.aws-ssm (<2.0.0,>=1.126.0)
Requires-Dist: aws-cdk.core (<2.0.0,>=1.126.0)
Requires-Dist: constructs (<4.0.0,>=3.2.27)
Requires-Dist: jsii (<2.0.0,>=1.36.0)
Requires-Dist: publication (>=0.0.3)
